LICENSE
MANIFEST.in
README.md
setup.py
django_mediamanager/__init__.py
django_mediamanager/context_processors.py
django_mediamanager/models.py
django_mediamanager.egg-info/PKG-INFO
django_mediamanager.egg-info/SOURCES.txt
django_mediamanager.egg-info/dependency_links.txt
django_mediamanager.egg-info/requires.txt
django_mediamanager.egg-info/top_level.txt