Metadata-Version: 1.0
Name: django-mediamanager
Version: 0.1.1
Summary: A central repository for Django apps to register any static media that needs to be included.
Home-page: https://github.com/jasonbeverage/django-mediamanager
Author: Jason Beverage
Author-email: UNKNOWN
License: UNKNOWN
Platform: UNKNOWN
